EasyForge/Authentication.py
EasyForge/DesignAutomation.py
EasyForge/ModelDerivative.py
EasyForge/__init__.py
EasyForge/DataManagement/ACC.py
EasyForge/DataManagement/OSS.py
EasyForge/DataManagement/__init__.py
EasyForge-0.0.2.dist-info/LICENSE.txt
EasyForge-0.0.2.dist-info/METADATA
EasyForge-0.0.2.dist-info/WHEEL
EasyForge-0.0.2.dist-info/top_level.txt
EasyForge-0.0.2.dist-info/RECORD
