Metadata-Version: 2.1
Name: EasyForge
Version: 0.0.2
Summary: To Make easy to use Forge (APS) by python
Author: DKVG
Author-email: gadellidk@gmail.com
Keywords: EasyForge forge APS forge-python python-aps
Classifier: Programming Language :: Python :: 3
Classifier: License :: OSI Approved :: MIT License
Classifier: Operating System :: OS Independent
Requires-Python: >=3.9
License-File: LICENSE.txt
